setup.py
GitLabL.py.egg-info/PKG-INFO
GitLabL.py.egg-info/SOURCES.txt
GitLabL.py.egg-info/dependency_links.txt
GitLabL.py.egg-info/top_level.txt
GitLabL.py.egg-info/zip-safe
QQ/__init__.py