Metadata-Version: 2.1
Name: GitLabL.py
Version: 1.131
Summary: [setup.py專案]
Home-page: UNKNOWN
Author: 我是一隻小貓
Author-email: 999@gmial.com
License: LGPL
Platform: UNKNOWN
